{
  "MANOSABA-NIKAIDO_HIRO.title": "Nikaido Hiro",
  "MANOSABA-NIKAIDO_HIRO.titleObject": "",
  "MANOSABA-NIKAIDO_HIRO.description": "You're wrong—I'm not evil. I'm the only one who can set this world right. I'll wipe out the evil of this world myself.",
  "MANOSABA-NIKAIDO_HIRO.pronounObject": "her",
  "MANOSABA-NIKAIDO_HIRO.possessiveAdjective": "her",
  "MANOSABA-NIKAIDO_HIRO.pronounPossessive": "her",
  "MANOSABA-NIKAIDO_HIRO.pronounSubject": "she",
  "MANOSABA-NIKAIDO_HIRO.goldMonologue": "",
  "MANOSABA-NIKAIDO_HIRO.eventDeathPrevention": "Did I loop back again?",
  "MANOSABA-NIKAIDO_HIRO.aromaPrinciple": "",
  "MANOSABA-NIKAIDO_HIRO.cardsModifierTitle": "",
  "MANOSABA-NIKAIDO_HIRO.cardsModifierDescription": "",
  "MANOSABA-NIKAIDO_HIRO.banter.alive.endTurnPing": "Hurry up and act!",
  "MANOSABA-NIKAIDO_HIRO.banter.dead.endTurnPing": "......",
  "MANOSABA-HIKAMI_MERURU.title": "Hikami Meruru",
  "MANOSABA-HIKAMI_MERURU.titleObject": "",
  "MANOSABA-HIKAMI_MERURU.description": "I just want everyone to smile, even a little. It's the only thing I can do...",
  "MANOSABA-HIKAMI_MERURU.pronounObject": "her",
  "MANOSABA-HIKAMI_MERURU.possessiveAdjective": "her",
  "MANOSABA-HIKAMI_MERURU.pronounPossessive": "her",
  "MANOSABA-HIKAMI_MERURU.pronounSubject": "she",
  "MANOSABA-HIKAMI_MERURU.goldMonologue": "",
  "MANOSABA-HIKAMI_MERURU.eventDeathPrevention": "",
  "MANOSABA-HIKAMI_MERURU.aromaPrinciple": "",
  "MANOSABA-HIKAMI_MERURU.cardsModifierTitle": "",
  "MANOSABA-HIKAMI_MERURU.cardsModifierDescription": "",
  "MANOSABA-HIKAMI_MERURU.banter.alive.endTurnPing": "I-it's okay... take your time...",
  "MANOSABA-HIKAMI_MERURU.banter.dead.endTurnPing": "......",
  "MANOSABA-JOGASAKI_NOAH.title": "Jogasaki Noah",
  "MANOSABA-JOGASAKI_NOAH.titleObject": "",
  "MANOSABA-JOGASAKI_NOAH.description": "Noah, not eating today? Noah's still only halfway done with her painting.",
  "MANOSABA-JOGASAKI_NOAH.pronounObject": "her",
  "MANOSABA-JOGASAKI_NOAH.possessiveAdjective": "her",
  "MANOSABA-JOGASAKI_NOAH.pronounPossessive": "her",
  "MANOSABA-JOGASAKI_NOAH.pronounSubject": "she",
  "MANOSABA-JOGASAKI_NOAH.goldMonologue": "",
  "MANOSABA-JOGASAKI_NOAH.eventDeathPrevention": "",
  "MANOSABA-JOGASAKI_NOAH.aromaPrinciple": "",
  "MANOSABA-JOGASAKI_NOAH.cardsModifierTitle": "",
  "MANOSABA-JOGASAKI_NOAH.cardsModifierDescription": "",
  "MANOSABA-JOGASAKI_NOAH.banter.alive.endTurnPing": "Hurry up!",
  "MANOSABA-JOGASAKI_NOAH.banter.dead.endTurnPing": "......",
  "MANOSABA-TACHIBANA_SHERRY.title": "Tachibana Sherry",
  "MANOSABA-TACHIBANA_SHERRY.titleObject": "",
  "MANOSABA-TACHIBANA_SHERRY.description": "Standing on the interesting side—that's my creed!",
  "MANOSABA-TACHIBANA_SHERRY.pronounObject": "",
  "MANOSABA-TACHIBANA_SHERRY.possessiveAdjective": "",
  "MANOSABA-TACHIBANA_SHERRY.pronounPossessive": "",
  "MANOSABA-TACHIBANA_SHERRY.pronounSubject": "",
  "MANOSABA-TACHIBANA_SHERRY.goldMonologue": "",
  "MANOSABA-TACHIBANA_SHERRY.eventDeathPrevention": "",
  "MANOSABA-TACHIBANA_SHERRY.aromaPrinciple": "",
  "MANOSABA-TACHIBANA_SHERRY.cardsModifierTitle": "",
  "MANOSABA-TACHIBANA_SHERRY.cardsModifierDescription": "",
  "MANOSABA-TACHIBANA_SHERRY.banter.alive.endTurnPing": "",
  "MANOSABA-TACHIBANA_SHERRY.banter.dead.endTurnPing": "",
  "MANOSABA-SAEKI_MIRIA.title": "Saeki Miria",
  "MANOSABA-SAEKI_MIRIA.titleObject": "",
  "MANOSABA-SAEKI_MIRIA.description": "U-um... I'm Saeki Miria, okay? Nice to meet you~ Ahaha~",
  "MANOSABA-SAEKI_MIRIA.pronounObject": "her",
  "MANOSABA-SAEKI_MIRIA.possessiveAdjective": "her",
  "MANOSABA-SAEKI_MIRIA.pronounPossessive": "hers",
  "MANOSABA-SAEKI_MIRIA.pronounSubject": "she",
  "MANOSABA-SAEKI_MIRIA.goldMonologue": "",
  "MANOSABA-SAEKI_MIRIA.eventDeathPrevention": "",
  "MANOSABA-SAEKI_MIRIA.aromaPrinciple": "",
  "MANOSABA-SAEKI_MIRIA.cardsModifierTitle": "",
  "MANOSABA-SAEKI_MIRIA.cardsModifierDescription": "",
  "MANOSABA-SAEKI_MIRIA.banter.alive.endTurnPing": "I-it's okay, mister... you can take your time.",
  "MANOSABA-SAEKI_MIRIA.banter.dead.endTurnPing": "...",

  "MANOSABA-HASUMI_LEIA.title": "Hasumi Leia",
  "MANOSABA-HASUMI_LEIA.titleObject": "",
  "MANOSABA-HASUMI_LEIA.description": "U-um... I'm Hasumi Leia, okay? Nice to meet you~ Ahaha~",
  "MANOSABA-HASUMI_LEIA.pronounObject": "her",
  "MANOSABA-HASUMI_LEIA.possessiveAdjective": "her",
  "MANOSABA-HASUMI_LEIA.pronounPossessive": "hers",
  "MANOSABA-HASUMI_LEIA.pronounSubject": "she",
  "MANOSABA-HASUMI_LEIA.goldMonologue": "",
  "MANOSABA-HASUMI_LEIA.eventDeathPrevention": "",
  "MANOSABA-HASUMI_LEIA.aromaPrinciple": "",
  "MANOSABA-HASUMI_LEIA.cardsModifierTitle": "",
  "MANOSABA-HASUMI_LEIA.cardsModifierDescription": "",
  "MANOSABA-HASUMI_LEIA.banter.alive.endTurnPing": "I-it's okay, mister... you can take your time.",
  "MANOSABA-HASUMI_LEIA.banter.dead.endTurnPing": "...",

  "MANOSABA-TONO_HANNA.title": "Tono Hanna",
  "MANOSABA-TONO_HANNA.titleObject": "",
  "MANOSABA-TONO_HANNA.description": "You're pitiful... I'd recommend you give up.",
  "MANOSABA-TONO_HANNA.pronounObject": "",
  "MANOSABA-TONO_HANNA.possessiveAdjective": "",
  "MANOSABA-TONO_HANNA.pronounPossessive": "",
  "MANOSABA-TONO_HANNA.pronounSubject": "",
  "MANOSABA-TONO_HANNA.goldMonologue": "",
  "MANOSABA-TONO_HANNA.eventDeathPrevention": "",
  "MANOSABA-TONO_HANNA.aromaPrinciple": "",
  "MANOSABA-TONO_HANNA.cardsModifierTitle": "",
  "MANOSABA-TONO_HANNA.cardsModifierDescription": "",
  "MANOSABA-TONO_HANNA.banter.alive.endTurnPing": "",
  "MANOSABA-TONO_HANNA.banter.dead.endTurnPing": "",
  "MANOSABA-HOSHO_MAGO.title": "Hosho Margo",
  "MANOSABA-HOSHO_MAGO.titleObject": "",
  "MANOSABA-HOSHO_MAGO.description": "So many cute little ones here... I can't help but lick my lips, hehe.",
  "MANOSABA-HOSHO_MAGO.pronounObject": "her",
  "MANOSABA-HOSHO_MAGO.possessiveAdjective": "her",
  "MANOSABA-HOSHO_MAGO.pronounPossessive": "hers",
  "MANOSABA-HOSHO_MAGO.pronounSubject": "she",
  "MANOSABA-HOSHO_MAGO.goldMonologue": "",
  "MANOSABA-HOSHO_MAGO.eventDeathPrevention": "",
  "MANOSABA-HOSHO_MAGO.aromaPrinciple": "",
  "MANOSABA-HOSHO_MAGO.cardsModifierTitle": "",
  "MANOSABA-HOSHO_MAGO.cardsModifierDescription": "",
  "MANOSABA-HOSHO_MAGO.banter.alive.endTurnPing": "How adorable!",
  "MANOSABA-HOSHO_MAGO.banter.dead.endTurnPing": "...",
  "MANOSABA.mod_title": "Manosaba"
}
